cryptotax/__init__.py
cryptotax/main.py
cryptotax-1.0a1.dist-info/DESCRIPTION.rst
cryptotax-1.0a1.dist-info/METADATA
cryptotax-1.0a1.dist-info/RECORD
cryptotax-1.0a1.dist-info/WHEEL
cryptotax-1.0a1.dist-info/metadata.json
cryptotax-1.0a1.dist-info/top_level.txt
