Metadata-Version: 2.0
Name: cryptotax
Version: 1.0a1
Summary: Cryptocurrency tracker
Home-page: UNKNOWN
Author: Amol Bhave
Author-email: ammubhave@gmail.com
License: UNKNOWN
Keywords: bitcoin cryptocurrency tax
Platform: UNKNOWN
Classifier: Development Status :: 1 - Planning
Classifier: Environment :: Console
Classifier: Intended Audience :: End Users/Desktop
Classifier: License :: OSI Approved :: GNU General Public License v3 (GPLv3)
Classifier: Programming Language :: Python :: 3
Classifier: Topic :: Office/Business :: Financial
Provides-Extra: dev
Requires-Dist: pre-commit; extra == 'dev'
